BringPythonApi/Bring.py
BringPythonApi/BringList.py
BringPythonApi/Exceptions.py
BringPythonApi/Item.py
BringPythonApi/User.py
BringPythonApi/__init__.py
bring_python_api-1.0.2.dist-info/LICENSE
bring_python_api-1.0.2.dist-info/METADATA
bring_python_api-1.0.2.dist-info/WHEEL
bring_python_api-1.0.2.dist-info/top_level.txt
bring_python_api-1.0.2.dist-info/RECORD
