Metadata-Version: 2.1
Name: bring-python-api
Version: 1.0.2
Summary: Bring! web api for Python
Home-page: https://github.com/Psychokiller1888/bring-api
Author: Psychokiller1888
Author-email: laurentchervet@bluewin.ch
Maintainer: Psychokiller1888
License: GPL-3.0
Platform: UNKNOWN
Classifier: Development Status :: 5 - Production/Stable
Classifier: Environment :: Web Environment
Classifier: Intended Audience :: Developers
Classifier: License :: OSI Approved :: GNU General Public License v3 (GPLv3)
Classifier: Operating System :: OS Independent
Classifier: Programming Language :: Python :: 3.8
Requires-Python: >=3.8
Requires-Dist: requests (~=2.26.0)
